caseconvertor/__init__.py
caseconvertor/boundaries.py
caseconvertor/camel.py
caseconvertor/camel_test.py
caseconvertor/caseconverter.py
caseconvertor/caseconverter_test.py
caseconvertor/cobol.py
caseconvertor/cobol_test.py
caseconvertor/flat.py
caseconvertor/flat_test.py
caseconvertor/kebab.py
caseconvertor/kebab_test.py
caseconvertor/macro.py
caseconvertor/macro_test.py
caseconvertor/pascal.py
caseconvertor/pascal_test.py
caseconvertor/snake.py
caseconvertor/snake_test.py
case_convertor-1.1.2.dist-info/LICENSE
case_convertor-1.1.2.dist-info/METADATA
case_convertor-1.1.2.dist-info/WHEEL
case_convertor-1.1.2.dist-info/top_level.txt
case_convertor-1.1.2.dist-info/RECORD
