Metadata-Version: 2.1
Name: case-convertor
Version: 1.1.2
Summary: A string case conversion package.
Home-page: https://github.com/chrisdoherty4/python-case-convertor
Author: Chris Doherty
Author-email: chris@chrisdoherty.io
Keywords: case,convert,converter,string
Classifier: Development Status :: 5 - Production/Stable
Classifier: License :: OSI Approved :: MIT License
Classifier: Natural Language :: English
Classifier: Topic :: Utilities
Classifier: Topic :: Text Processing
Classifier: Programming Language :: Python :: 3
License-File: LICENSE
